LICENSE.txt
README.md
setup.cfg
setup.py
Ejercicio13/__init__.py
Ejercicio13/operaciones.py
Ejercicio13_Enunciados_PedroZambudio.egg-info/PKG-INFO
Ejercicio13_Enunciados_PedroZambudio.egg-info/SOURCES.txt
Ejercicio13_Enunciados_PedroZambudio.egg-info/dependency_links.txt
Ejercicio13_Enunciados_PedroZambudio.egg-info/requires.txt
Ejercicio13_Enunciados_PedroZambudio.egg-info/top_level.txt