Metadata-Version: 2.4
Name: Ejercicio13_Enunciados_PedroZambudio
Version: 0.1
Summary: Ejercicio 13
Home-page: https://github.com/RobertoCoronaEscamilla/libreria_rc
Download-URL: https://github.com/RobertoCoronaEscamilla/libreria_rc.git
Author: Pedro Javier Zambudio Decillis
Author-email: pjzambudio@gmail.com
License: MIT
Keywords: operaciones,suma,resta,multiplicacion,division
Classifier: Development Status :: 3 - Alpha
Classifier: Intended Audience :: Developers
Classifier: Topic :: Software Development :: Build Tools
Classifier: License :: OSI Approved :: MIT License
Classifier: Programming Language :: Python :: 3
Classifier: Programming Language :: Python :: 3.4
Classifier: Programming Language :: Python :: 3.5
Classifier: Programming Language :: Python :: 3.6
License-File: LICENSE.txt
Requires-Dist: pytest
Dynamic: author
Dynamic: author-email
Dynamic: classifier
Dynamic: download-url
Dynamic: home-page
Dynamic: keywords
Dynamic: license
Dynamic: license-file
Dynamic: requires-dist
Dynamic: summary
